LICENSE
README.rst
pyproject.toml
setup.cfg
setup.py
pylint_google_style_guide_imports_enforcing/__init__.py
pylint_google_style_guide_imports_enforcing/test_checker.py
pylint_google_style_guide_imports_enforcing/test_ignoring_imports_from_future.py
pylint_google_style_guide_imports_enforcing.egg-info/PKG-INFO
pylint_google_style_guide_imports_enforcing.egg-info/SOURCES.txt
pylint_google_style_guide_imports_enforcing.egg-info/dependency_links.txt
pylint_google_style_guide_imports_enforcing.egg-info/top_level.txt