Metadata-Version: 2.1
Name: pylint-google-style-guide-imports-enforcing
Version: 1.3.1
Summary: Plugin for PyLint that checks if we import only modules or packages. Direct imports of classes, functions and constants are forbidden
Home-page: https://github.com/Enforcer/pylint_google_style_guide_imports_enforcing
Author: Sebastian Buczyński
Author-email: nnplaya@gmail.com
License: UNKNOWN
Download-URL: https://github.com/Enforcer/pylint_google_style_guide_imports_enforcing/archive/1.2.0.tar.gz
Keywords: pylint,google style guide,imports
Platform: UNKNOWN
License-File: LICENSE
